<?xml version="1.0" encoding="UTF-8"?>
<objects serializationModel="Studio.02.00.00">
	<object class="MixerMaster" id="{2c906215-2c4e-4756-a1d3-2c99f801bc88}">
		<property name="name">
			<value>Master Bus</value>
		</property>
		<relationship name="effectChain">
			<destination>{b017235e-c00f-4688-b4e5-f60a5a6b0652}</destination>
		</relationship>
		<relationship name="panner">
			<destination>{34f39827-d639-4757-ab4e-d15cc8a6f00c}</destination>
		</relationship>
		<relationship name="mixer">
			<destination>{87a04f58-332e-428a-9720-4e2c7ed6baa6}</destination>
		</relationship>
	</object>
	<object class="MixerBusEffectChain" id="{b017235e-c00f-4688-b4e5-f60a5a6b0652}">
		<relationship name="effects">
			<destination>{779b7901-3a08-4dab-a570-f24622b7b893}</destination>
		</relationship>
	</object>
	<object class="MixerBusPanner" id="{34f39827-d639-4757-ab4e-d15cc8a6f00c}">
		<property name="overridingOutputFormat">
			<value>2</value>
		</property>
		<property name="outputFormatOverridden">
			<value>true</value>
		</property>
	</object>
	<object class="MixerBusFader" id="{779b7901-3a08-4dab-a570-f24622b7b893}" />
</objects>
